{
  "project_info": {
    "project_number": "187910044168",
    "project_id": "fir-tutorial-20a0c",
    "storage_bucket": "fir-tutorial-20a0c.appspot.com"
  },
  "client": [
    {
      "client_info": {
        "mobilesdk_app_id": "1:187910044168:android:3c3abc81973042c1472fbd",
        "android_client_info": {
          "package_name": "com.tutorial.tutorialfirebase"
        }
      },
      "oauth_client": [],
      "api_key": [
        {
          "current_key": "AIzaSyAqilOkwRJgZGgh1ZcahcHHtzgfmhTK45Q"
        }
      ],
      "services": {
        "appinvite_service": {
          "other_platform_oauth_client": []
        }
      }
    }
  ],
  "configuration_version": "1"
}